gal/__init__.py
gal/compatibility.py
gal/config.py
gal/manager.py
gal/provider.py
gal/parsers/__init__.py
gal/parsers/haproxy_parser.py
gal/providers/__init__.py
gal/providers/apisix.py
gal/providers/envoy.py
gal/providers/haproxy.py
gal/providers/kong.py
gal/providers/nginx.py
gal/providers/traefik.py
gal_gateway-1.3.0.dist-info/licenses/LICENSE
gal_gateway-1.3.0.dist-info/METADATA
gal_gateway-1.3.0.dist-info/WHEEL
gal_gateway-1.3.0.dist-info/entry_points.txt
gal_gateway-1.3.0.dist-info/top_level.txt
gal_gateway-1.3.0.dist-info/RECORD
