Metadata-Version: 2.4
Name: gal-gateway
Version: 1.3.0
Summary: Gateway Abstraction Layer - Provider-agnostic API Gateway configuration system
Home-page: https://github.com/pt9912/x-gal
Author: Dietmar Burkard
Author-email: 
License: MIT
Project-URL: Homepage, https://github.com/pt9912/x-gal
Project-URL: Documentation, https://pt9912.github.io/x-gal/
Project-URL: Repository, https://github.com/pt9912/x-gal
Project-URL: Bug Tracker, https://github.com/pt9912/x-gal/issues
Project-URL: Changelog, https://github.com/pt9912/x-gal/blob/main/CHANGELOG.md
Keywords: api-gateway,envoy,kong,apisix,traefik,gateway,configuration,abstraction,devops,infrastructure,rate-limiting,authentication,cors,circuit-breaker,health-checks,load-balancing,jwt,security
Classifier: Development Status :: 5 - Production/Stable
Classifier: Intended Audience :: Developers
Classifier: Intended Audience :: System Administrators
Classifier: Topic :: Software Development :: Code Generators
Classifier: Topic :: System :: Networking
Classifier: Topic :: Internet :: WWW/HTTP :: HTTP Servers
Classifier: Topic :: Security
Classifier: License :: OSI Approved :: MIT License
Classifier: Programming Language :: Python :: 3
Classifier: Programming Language :: Python :: 3.10
Classifier: Programming Language :: Python :: 3.11
Classifier: Programming Language :: Python :: 3.12
Classifier: Operating System :: OS Independent
Classifier: Environment :: Console
Classifier: Typing :: Typed
Classifier: Framework :: AsyncIO
Requires-Python: >=3.10
License-File: LICENSE
Requires-Dist: click>=8.1.0
Requires-Dist: pyyaml>=6.0
Requires-Dist: requests>=2.31.0
Provides-Extra: dev
Requires-Dist: pytest>=8.0.0; extra == "dev"
Requires-Dist: pytest-cov>=4.1.0; extra == "dev"
Requires-Dist: black>=24.0.0; extra == "dev"
Requires-Dist: flake8>=7.0.0; extra == "dev"
Requires-Dist: isort>=5.13.0; extra == "dev"
Requires-Dist: mkdocs>=1.5.0; extra == "dev"
Requires-Dist: mkdocs-material>=9.0.0; extra == "dev"
Dynamic: home-page
Dynamic: license-file
Dynamic: requires-python
